Workbook

Sheet DATA
A1: YEAR | B1: OWN TAX REVENUE | C1: OWN NON-TAX REVENUE | D1: REVENUE RECEIPT | E1: REVENUE EXPENDITURE | F1: CAPITAL EXPENDITURE | G1: TOTAL EXPENDITURE | H1: REVENUE DEFICIT | I1: FISCAL DEFICIT | J1: GSDP AT CURRENT PRICES | K1: REVENUE RECEIPT RATIO | L1: REVENUE EXPENDITURE RATIO | M1: CAPITAL EXPENDITURE RATIO | N1: TOTAL EXPENDITURE RATIO | O1: REVENUE DEFICIT RATIO | P1: FISCAL DEFICIT RATIO | Q1: PERIOD | R1: CAPITAL EXPENDITURE AS % OF TOTAL EXPENDITURE
A2: 2005-2006 | B2: 9779.64 | C2: 936.77 | D2: 15294.52 | E2: 18423.58 | F2: 1104.06 | G2: =E2+F2 -> 19527.64 | H2: 3129.15 | I2: 4181.72 | J2: 124389.42 | K2: =(D2/J2)*100 -> 12.295676 | L2: =(E2/J2)*100 -> 14.811211 | M2: =(F2/J2)*100 -> 0.88758353 | N2: =(G2/J2)*100 -> 15.698795 | O2: =(H2/J2)*100 -> 2.5156078 | P2: =(I2/J2)*100 -> 3.3617972 | Q2: PRE-GST | R2: =F2/G2 -> 0.056538322
A3: =LEFT(A2,4)+1&"-"&RIGHT(A2,4)+1 -> 2006-2007 | B3: 11941.82 | C3: 937.57 | D3: 18186.62 | E3: 20824.57 | F3: 1251.97 | G3: =E3+F3 -> 22076.54 | H3: 2637.95 | I3: 3821.87 | J3: 142470.04 | K3: =(D3/J3)*100 -> 12.765224 | L3: =(E3/J3)*100 -> 14.616806 | M3: =(F3/J3)*100 -> 0.87876019 | N3: =(G3/J3)*100 -> 15.495567 | O3: =(H3/J3)*100 -> 1.8515823 | P3: =(I3/J3)*100 -> 2.682578 | Q3: PRE-GST | R3: =F3/G3 -> 0.056710427
A4: =LEFT(A3,4)+1&"-"&RIGHT(A3,4)+1 -> 2007-2008 | B4: 13668.95 | C4: 1209.55 | D4: 21106.79 | E4: 24891.64 | F4: 2367.74 | G4: =E4+F4 -> 27259.38 | H4: 3784.84 | I4: 6100.21 | J4: 175141.08 | K4: =(D4/J4)*100 -> 12.051307 | L4: =(E4/J4)*100 -> 14.212337 | M4: =(F4/J4)*100 -> 1.3519044 | N4: =(G4/J4)*100 -> 15.564241 | O4: =(H4/J4)*100 -> 2.1610236 | P4: =(I4/J4)*100 -> 3.4830264 | Q4: PRE-GST | R4: =F4/G4 -> 0.086859642
A5: =LEFT(A4,4)+1&"-"&RIGHT(A4,4)+1 -> 2008-2009 | B5: 15990.18 | C5: 1559.29 | D5: 24512.18 | E5: 28223.85 | F5: 2679.29 | G5: =E5+F5 -> 30903.14 | H5: 3711.67 | I5: 6346.21 | J5: 201019.75 | K5: =(D5/J5)*100 -> 12.193916 | L5: =(E5/J5)*100 -> 14.040337 | M5: =(F5/J5)*100 -> 1.3328491 | N5: =(G5/J5)*100 -> 15.373186 | O5: =(H5/J5)*100 -> 1.8464206 | P5: =(I5/J5)*100 -> 3.1570082 | Q5: PRE-GST | R5: =F5/G5 -> 0.086699604
A6: =LEFT(A5,4)+1&"-"&RIGHT(A5,4)+1 -> 2009-2010 | B6: 17625.02 | C6: 1852.22 | D6: 26109.4 | E6: 31132.38 | F6: 2936.06 | G6: =E6+F6 -> 34068.44 | H6: 5022.97 | I6: 7871.6 | J6: 230315.55 | K6: =(D6/J6)*100 -> 11.33636 | L6: =(E6/J6)*100 -> 13.517272 | M6: =(F6/J6)*100 -> 1.2747989 | N6: =(G6/J6)*100 -> 14.792071 | O6: =(H6/J6)*100 -> 2.1809079 | P6: =(I6/J6)*100 -> 3.4177458 | Q6: PRE-GST | R6: =F6/G6 -> 0.086181228
A7: =LEFT(A6,4)+1&"-"&RIGHT(A6,4)+1 -> 2010-2011 | B7: 21721.69 | C7: 1930.79 | D7: 30990.95 | E7: 34664.81 | F7: 4125.43 | G7: =E7+F7 -> 38790.24 | H7: =E7-D7 -> 3673.86 | I7: 7730.46 | J7: 276996.7 | K7: =(D7/J7)*100 -> 11.188202 | L7: =(E7/J7)*100 -> 12.514521 | M7: =(F7/J7)*100 -> 1.4893427 | N7: =(G7/J7)*100 -> 14.003864 | O7: =(H7/J7)*100 -> 1.3263191 | P7: =(I7/J7)*100 -> 2.790813 | Q7: PRE-GST | R7: =F7/G7 -> 0.10635227
A8: =LEFT(A7,4)+1&"-"&RIGHT(A7,4)+1 -> 2011-2012 | B8: 25718.6 | C8: 2592.18 | D8: 38010.36 | E8: 46044.62 | F8: 4851.46 | G8: =E8+F8 -> 50896.08 | H8: =E8-D8 -> 8034.26 | I8: 12814.77 | J8: =36404788/100 -> 364047.88 | K8: =(D8/J8)*100 -> 10.441033 | L8: =(E8/J8)*100 -> 12.647957 | M8: =(F8/J8)*100 -> 1.3326434 | N8: =(G8/J8)*100 -> 13.980601 | O8: =(H8/J8)*100 -> 2.206924 | P8: =(I8/J8)*100 -> 3.5200782 | Q8: PRE-GST | R8: =F8/G8 -> 0.095320897
A9: =LEFT(A8,4)+1&"-"&RIGHT(A8,4)+1 -> 2012-2013 | B9: 30076.61 | C9: 4198.52 | D9: 44137.31 | E9: 53488.74 | F9: 5739.44 | G9: =E9+F9 -> 59228.18 | H9: =E9-D9 -> 9351.43 | I9: 15002.47 | J9: =41231300/100 -> 412313 | K9: =(D9/J9)*100 -> 10.704807 | L9: =(E9/J9)*100 -> 12.972848 | M9: =(F9/J9)*100 -> 1.3920104 | N9: =(G9/J9)*100 -> 14.364859 | O9: =(H9/J9)*100 -> 2.2680415 | P9: =(I9/J9)*100 -> 3.6386119 | Q9: PRE-GST | R9: =F9/G9 -> 0.096903872
A10: =LEFT(A9,4)+1&"-"&RIGHT(A9,4)+1 -> 2013-2014 | B10: 31995.02 | C10: 5575.03 | D10: 49176.94 | E10: 60485.5 | F10: 5758.5 | G10: =E10+F10 -> 66244 | H10: =E10-D10 -> 11308.56 | I10: 16944.12 | J10: =46504121/100 -> 465041.21 | K10: =(D10/J10)*100 -> 10.574749 | L10: =(E10/J10)*100 -> 13.006482 | M10: =(F10/J10)*100 -> 1.2382774 | N10: =(G10/J10)*100 -> 14.244759 | O10: =(H10/J10)*100 -> 2.4317329 | P10: =(I10/J10)*100 -> 3.6435739 | Q10: PRE-GST | R10: =F10/G10 -> 0.086928627
A11: =LEFT(A10,4)+1&"-"&RIGHT(A10,4)+1 -> 2014-2015 | B11: 35232.5 | C11: 7283.69 | D11: 57950.47 | E11: 71746.43 | F11: 4997.68 | G11: =E11+F11 -> 76744.11 | H11: =E11-D11 -> 13795.96 | I11: 18641.73 | J11: =51256405/100 -> 512564.05 | K11: =(D11/J11)*100 -> 11.305996 | L11: =(E11/J11)*100 -> 13.997554 | M11: =(F11/J11)*100 -> 0.97503522 | N11: =(G11/J11)*100 -> 14.972589 | O11: =(H11/J11)*100 -> 2.6915583 | P11: =(I11/J11)*100 -> 3.6369562 | Q11: PRE-GST | R11: =F11/G11 -> 0.065121349
A12: =LEFT(A11,4)+1&"-"&RIGHT(A11,4)+1 -> 2015-2016 | B12: 38995.15 | C12: 8425.49 | D12: 69032.66 | E12: 78689.47 | F12: 8342.29 | G12: =E12+F12 -> 87031.76 | H12: =E12-D12 -> 9656.81 | I12: 17818.39 | J12: =56199361/100 -> 561993.61 | K12: =(D12/J12)*100 -> 12.283531 | L12: =(E12/J12)*100 -> 14.001844 | M12: =(F12/J12)*100 -> 1.4844101 | N12: =(G12/J12)*100 -> 15.486254 | O12: =(H12/J12)*100 -> 1.7183131 | P12: =(I12/J12)*100 -> 3.1705681 | Q12: PRE-GST | R12: =F12/G12 -> 0.095853399
A13: =LEFT(A12,4)+1&"-"&RIGHT(A12,4)+1 -> 2016-2017 | B13: 42176.38 | C13: 9699.98 | D13: 75611.72 | E13: 91096.31 | F13: 11286.25 | G13: =E13+F13 -> 102382.56 | H13: =E13-D13 -> 15484.59 | I13: 26448.35 | J13: =63488640/100 -> 634886.4 | K13: =(D13/J13)*100 -> 11.909488 | L13: =(E13/J13)*100 -> 14.348442 | M13: =(F13/J13)*100 -> 1.7776802 | N13: =(G13/J13)*100 -> 16.126123 | O13: =(H13/J13)*100 -> 2.4389544 | P13: =(I13/J13)*100 -> 4.1658397 | Q13: PRE-GST | R13: =F13/G13 -> 0.11023606
A14: =LEFT(A13,4)+1&"-"&RIGHT(A13,4)+1 -> 2017-2018 | B14: 46459.61 | C14: 11199.61 | D14: 83020.14 | E14: 99948.35 | F14: 10289.46 | G14: =E14+F14 -> 110237.81 | H14: =E14-D14 -> 16928.21 | I14: 26837.41 | J14: =70158826/100 -> 701588.26 | K14: =(D14/J14)*100 -> 11.833171 | L14: =(E14/J14)*100 -> 14.246012 | M14: =(F14/J14)*100 -> 1.4665952 | N14: =(G14/J14)*100 -> 15.712608 | O14: =(H14/J14)*100 -> 2.4128411 | P14: =(I14/J14)*100 -> 3.8252365 | Q14: GST | R14: =F14/G14 -> 0.093338756
A15: =LEFT(A14,4)+1&"-"&RIGHT(A14,4)+1 -> 2018-2019 | B15: 50644.1 | C15: 11783.24 | D15: 92854.47 | E15: 110316.39 | F15: 9753.43 | G15: =E15+F15 -> 120069.82 | H15: =E15-D15 -> 17461.92 | I15: 26958.3 | J15: =78828558/100 -> 788285.58 | K15: =(D15/J15)*100 -> 11.779293 | L15: =(E15/J15)*100 -> 13.99447 | M15: =(F15/J15)*100 -> 1.2372965 | N15: =(G15/J15)*100 -> 15.231767 | O15: =(H15/J15)*100 -> 2.2151769 | P15: =(I15/J15)*100 -> 3.4198647 | Q15: GST | R15: =F15/G15 -> 0.08123132
A16: =LEFT(A15,4)+1&"-"&RIGHT(A15,4)+1 -> 2019-2020 | B16: 50323.14 | C16: 12265.22 | D16: 90224.67 | E16: 104719.92 | F16: 9665.02 | G16: =E16+F16 -> 114384.94 | H16: =E16-D16 -> 14495.25 | I16: 23837.48 | J16: =81293463/100 -> 812934.63 | K16: =(D16/J16)*100 -> 11.098638 | L16: =(E16/J16)*100 -> 12.881715 | M16: =(F16/J16)*100 -> 1.1889049 | N16: =(G16/J16)*100 -> 14.07062 | O16: =(H16/J16)*100 -> 1.7830769 | P16: =(I16/J16)*100 -> 2.9322751 | Q16: GST | R16: =F16/G16 -> 0.084495564
A17: =LEFT(A16,4)+1&"-"&RIGHT(A16,4)+1 -> 2020-2021 | B17: 47660.84 | C17: 7327.31 | D17: 97616.83 | E17: 123446.33 | F17: 15438.16 | G17: =E17+F17 -> 138884.49 | H17: =E17-D17 -> 25829.5 | I17: 35203.69 | J17: =77172389/100 -> 771723.89 | K17: =(D17/J17)*100 -> 12.649191 | L17: =(E17/J17)*100 -> 15.996178 | M17: =(F17/J17)*100 -> 2.0004771 | N17: =(G17/J17)*100 -> 17.996656 | O17: =(H17/J17)*100 -> 3.3469872 | P17: =(I17/J17)*100 -> 4.561695 | Q17: COVID | R17: =F17/G17 -> 0.11115827
A18: =LEFT(A17,4)+1&"-"&RIGHT(A17,4)+1 -> 2021-2022 | B18: 58340.52 | C18: 10462.51 | D18: 116640.24 | E18: 146179.51 | F18: 17046.02 | G18: =E18+F18 -> 163225.53 | H18: =E18-D18 -> 29539.27 | I18: 37306.47 | J18: =92446542/100 -> 924465.42 | K18: =(D18/J18)*100 -> 12.617047 | L18: =(E18/J18)*100 -> 15.812329 | M18: =(F18/J18)*100 -> 1.8438786 | N18: =(G18/J18)*100 -> 17.656207 | O18: =(H18/J18)*100 -> 3.1952812 | P18: =(I18/J18)*100 -> 4.0354641 | Q18: COVID | R18: =F18/G18 -> 0.10443232
A19: =LEFT(A18,4)+1&"-"&RIGHT(A18,4)+1 -> 2022-2023 | B19: 71968.16 | C19: 15117.96 | D19: 132724.65 | E19: 141950.94 | F19: 16787.49 | G19: =E19+F19 -> 158738.43 | H19: =E19-D19 -> 9226.29 | I19: 25554.54 | J19: =103873406/100 -> 1038734.1 | K19: =(D19/J19)*100 -> 12.777539 | L19: =(E19/J19)*100 -> 13.665763 | M19: =(F19/J19)*100 -> 1.616149 | N19: =(G19/J19)*100 -> 15.281912 | O19: =(H19/J19)*100 -> 0.88822446 | P19: =(I19/J19)*100 -> 2.4601619 | Q19: RECOVERY | R19: =F19/G19 -> 0.10575568
A20: =LEFT(A19,4)+1&"-"&RIGHT(A19,4)+1 -> 2023-2024 | B20: 74329.01 | C20: 16345.96 | D20: 124486.15 | E20: 142626.34 | F20: 16880.17 | G20: =E20+F20 -> 159506.51 | H20: =E20-D20 -> 18140.19 | I20: 34258.05 | J20: =113537156/100 -> 1135371.6 | K20: =(D20/J20)*100 -> 10.964353 | L20: =(E20/J20)*100 -> 12.562085 | M20: =(F20/J20)*100 -> 1.4867529 | N20: =(G20/J20)*100 -> 14.048838 | O20: =(H20/J20)*100 -> 1.5977316 | P20: =(I20/J20)*100 -> 3.0173426 | Q20: RECOVERY | R20: =F20/G20 -> 0.10582747
A21: =LEFT(A20,4)+1&"-"&RIGHT(A20,4)+1 -> 2024-2025 | B21: 76642.2 | C21: 16486.62 | D21: 124861.07 | E21: 155920.79 | F21: 17886.77 | G21: =E21+F21 -> 173807.56 | H21: =E21-D21 -> 31059.72 | I21: 48248.14 | J21: =124853301/100 -> 1248533 | K21: =(D21/J21)*100 -> 10.000622 | L21: =(E21/J21)*100 -> 12.488319 | M21: =(F21/J21)*100 -> 1.4326229 | N21: =(G21/J21)*100 -> 13.920942 | O21: =(H21/J21)*100 -> 2.4876971 | P21: =(I21/J21)*100 -> 3.8643864 | Q21: RECOVERY | R21: =F21/G21 -> 0.10291135

Sheet ANALYSIS
A1: VARIABLE | B1: MEAN | C1: MEDIAN | D1: SD | E1: MIN | F1: MAX | G1: CAGR
A2: OWN TAX REVENUE | B2: =AVERAGE(DATA!B2:B21) -> 38564.457 | C2: =MEDIAN(DATA!B2:B21) -> 37113.825 | D2: =_xlfn.STDEV.S(DATA!B2:B21) -> 20974.4 | E2: =MIN(DATA!B2:B21) -> 9779.64 | F2: =MAX(DATA!B2:B21) -> 76642.2 | G2: =((DATA!B21/DATA!B2)^(1/19))-1 -> 0.11444918
A3: OWN NON-TAX REVENUE | B3: =AVERAGE(DATA!C2:C21) -> 7359.4755 | C3: =MEDIAN(DATA!C2:C21) -> 7305.5 | D3: =_xlfn.STDEV.S(DATA!C2:C21) -> 5373.1672 | E3: =MIN(DATA!C2:C21) -> 936.77 | F3: =MAX(DATA!C2:C21) -> 16486.62
A4: REVENUE RECEIPT | B4: =AVERAGE(DATA!D2:D21) -> 66627.407 | C4: =MEDIAN(DATA!D2:D21) -> 63491.565 | D4: =_xlfn.STDEV.S(DATA!D2:D21) -> 39478.701 | E4: =MIN(DATA!D2:D21) -> 15294.52 | F4: =MAX(DATA!D2:D21) -> 132724.65 | G4: =((DATA!D21/DATA!D2)^(1/19))-1 -> 0.11684852
A5: REVENUE EXPENDITURE | B5: =AVERAGE(DATA!E2:E21) -> 79241.023 | C5: =MEDIAN(DATA!E2:E21) -> 75217.95 | D5: =_xlfn.STDEV.S(DATA!E2:E21) -> 46787.222 | E5: =MIN(DATA!E2:E21) -> 18423.58 | F5: =MAX(DATA!E2:E21) -> 155920.79 | G5: =(DATA!E21/DATA!E2)^(1/19)-1 -> 0.11896723
A6: CAPITAL EXPENDITURE | B6: =AVERAGE(DATA!F2:F21) -> 8459.3345 | C6: =MEDIAN(DATA!F2:F21) -> 7050.395 | D6: =_xlfn.STDEV.S(DATA!F2:F21) -> 5765.6299 | E6: =MIN(DATA!F2:F21) -> 1104.06 | F6: =MAX(DATA!F2:F21) -> 17886.77 | G6: =((DATA!F21/DATA!F2)^(1/19))-1 -> 0.15787042
A7: TOTAL EXPENDITURE | B7: =AVERAGE(DATA!G2:G21) -> 87700.358 | C7: =MEDIAN(DATA!G2:G21) -> 81887.935 | D7: =_xlfn.STDEV.S(DATA!G2:G21) -> 52451.434 | E7: =MIN(DATA!G2:G21) -> 19527.64 | F7: =MAX(DATA!G2:G21) -> 173807.56 | G7: =((DATA!G21/DATA!G2)^(1/19))-1 -> 0.12193944
A8: REVENUE DEFICIT | B8: =AVERAGE(DATA!H2:H21) -> 12613.62 | C8: =MEDIAN(DATA!H2:H21) -> 10482.685 | D8: =_xlfn.STDEV.S(DATA!H2:H21) -> 8660.1695 | E8: =MIN(DATA!H2:H21) -> 2637.95 | F8: =MAX(DATA!H2:H21) -> 31059.72 | G8: =((DATA!H21/DATA!H2)^(1/19))-1 -> 0.12839626
A9: FISCAL DEFICIT | B9: =AVERAGE(DATA!I2:I21) -> 20096.299 | C9: =MEDIAN(DATA!I2:I21) -> 18230.06 | D9: =_xlfn.STDEV.S(DATA!I2:I21) -> 12556.868 | E9: =MIN(DATA!I2:I21) -> 3821.87 | F9: =MAX(DATA!I2:I21) -> 48248.14 | G9: =((DATA!I21/DATA!I2)^(1/19))-1 -> 0.1373689
A10: GSDP | B10: =AVERAGE(DATA!J2:J21) -> 576140.76 | C10: =MEDIAN(DATA!J2:J21) -> 537278.83 | D10: =_xlfn.STDEV.S(DATA!J2:J21) -> 344111.92 | E10: =MIN(DATA!J2:J21) -> 124389.42 | F10: =MAX(DATA!J2:J21) -> 1248533 | G10: =(DATA!J21/DATA!J2)^(1/19)-1 -> 0.12905907
A11: CAPITAL EXPENDITURE % | B11: =AVERAGE(DATA!R2:R21) -> 0.090942821 | C11: =MEDIAN(DATA!R2:R21) -> 0.094329826 | D11: =_xlfn.STDEV.S(DATA!R2:R21) -> 0.016384693 | E11: =MIN(DATA!R2:R21) -> 0.056538322 | F11: =MAX(DATA!R2:R21) -> 0.11115827

Sheet CHARTS

Sheet CORRELATION
B1: OWN TAX REVENUE | C1: OWN NON-TAX REVENUE | D1: REVENUE RECEIPT | E1: REVENUE EXPENDITURE | F1: CAPITAL EXPENDITURE | G1: TOTAL EXPENDITURE | H1: REVENUE DEFICIT | I1: FISCAL DEFICIT | J1: GSDP AT CURRENT PRICES
A2: OWN TAX REVENUE | B2: 1
A3: OWN NON-TAX REVENUE | B3: 0.974282 | C3: 1
A4: REVENUE RECEIPT | B4: 0.98676903 | C4: 0.95715547 | D4: 1
A5: REVENUE EXPENDITURE | B5: 0.97881416 | C5: 0.94378155 | D5: 0.99415729 | E5: 1
A6: CAPITAL EXPENDITURE | B6: 0.95711127 | C6: 0.89574996 | D6: 0.97511372 | E6: 0.98026144 | F6: 1
A7: TOTAL EXPENDITURE | B7: 0.97832109 | C7: 0.94032661 | D7: 0.99398621 | E7: 0.99976382 | F7: 0.98432655 | G7: 1
A8: REVENUE DEFICIT | B8: 0.78978011 | C8: 0.73551182 | D8: 0.81235718 | E8: 0.87055779 | F8: 0.85073172 | G8: 0.87006171 | H8: 1
A9: FISCAL DEFICIT | B9: 0.9227258 | C9: 0.8815363 | D9: 0.92652862 | E9: 0.95911833 | F9: 0.94589757 | G9: 0.95951956 | H9: 0.95798706 | I9: 1
A10: GSDP AT CURRENT PRICES | B10: 0.99614071 | C10: 0.97121734 | D10: 0.98574768 | E10: 0.98540521 | F10: 0.96058798 | G10: 0.98458255 | H10: 0.8300448 | I10: 0.94620288 | J10: 1

Sheet PERIOD ANALYSIS
A3: PERIOD | B3: REVENUE RECEIPT RATIO | C3: REVENUE EXP RATIO | D3: CAPITAL EXP RATIO | E3: TOTAL EXP RATIO | F3: REVENUE DEFICIT RATIO | G3: FISCAL DEFICIT RATIO
A4: PRE-GST | B4: 11.587524 | C4: 13.723968 | D4: 1.284608 | E4: 15.008576 | F4: 2.1364488 | G4: 3.3890497
A5: GST | B5: 11.570367 | C5: 13.707399 | D5: 1.2975989 | E5: 15.004998 | F5: 2.1370317 | G5: 3.3924588
A6: COVID | B6: 12.633119 | C6: 15.904253 | D6: 1.9221779 | E6: 17.826431 | F6: 3.2711342 | G6: 4.2985795
A7: RECOVERY | B7: 11.247505 | C7: 12.905389 | D7: 1.5118416 | E7: 14.417231 | F7: 1.6578844 | G7: 3.1139637

Sheet GROWTH
A1: YEAR | B1: OWN TAX REVENUE | C1: OWN TAX REVENUE GROWTH% | D1: REVENUE RECEIPT | E1: REVENUE RECEIPT GROWTH% | F1: REVENUE EXPENDITURE | G1: REVENUE EXPENDITURE GROWTH% | H1: GSDP | I1: GSDP GROWTH% | J1: CAPITAL EXPENDITURE | K1: CAPITAL EXPENDITURE GROWTH % | L1: FISCAL DEFICIT | M1: FISCAL DEFICIT GROWTH%
A2: 2005-2006 | B2: 9779.64 | D2: 15294.52 | F2: 18423.58 | H2: 124389.42 | J2: 1104.06 | L2: 4181.72
A3: =LEFT(A2,4)+1&"-"&RIGHT(A2,4)+1 -> 2006-2007 | B3: 11941.82 | C3: =(B3-B2)/B2 -> 0.22108994 | D3: 18186.62 | E3: =(D3-D2)/D2 -> 0.18909387 | F3: 20824.57 | G3: =(F3-F2)/F2 -> 0.13032158 | H3: 142470.04 | I3: =(H3-H2)/H2 -> 0.14535497 | J3: 1251.97 | K3: =(J3-J2)/J2 -> 0.13396917 | L3: 3821.87 | M3: =(L3-L2)/L2 -> -0.086053107
A4: =LEFT(A3,4)+1&"-"&RIGHT(A3,4)+1 -> 2007-2008 | B4: 13668.95 | C4: =(B4-B3)/B3 -> 0.14462871 | D4: 21106.79 | E4: =(D4-D3)/D3 -> 0.16056694 | F4: 24891.64 | G4: =(F4-F3)/F3 -> 0.19530151 | H4: 175141.08 | I4: =(H4-H3)/H3 -> 0.22931867 | J4: 2367.74 | K4: =(J4-J3)/J3 -> 0.89121145 | L4: 6100.21 | M4: =(L4-L3)/L3 -> 0.59613226
A5: =LEFT(A4,4)+1&"-"&RIGHT(A4,4)+1 -> 2008-2009 | B5: 15990.18 | C5: =(B5-B4)/B4 -> 0.16981773 | D5: 24512.18 | E5: =(D5-D4)/D4 -> 0.16134097 | F5: 28223.85 | G5: =(F5-F4)/F4 -> 0.13386864 | H5: 201019.75 | I5: =(H5-H4)/H4 -> 0.147759 | J5: 2679.29 | K5: =(J5-J4)/J4 -> 0.13158117 | L5: 6346.21 | M5: =(L5-L4)/L4 -> 0.040326481
A6: =LEFT(A5,4)+1&"-"&RIGHT(A5,4)+1 -> 2009-2010 | B6: 17625.02 | C6: =(B6-B5)/B5 -> 0.10224025 | D6: 26109.4 | E6: =(D6-D5)/D5 -> 0.065160259 | F6: 31132.38 | G6: =(F6-F5)/F5 -> 0.10305221 | H6: 230315.55 | I6: =(H6-H5)/H5 -> 0.14573593 | J6: 2936.06 | K6: =(J6-J5)/J5 -> 0.095835091 | L6: 7871.6 | M6: =(L6-L5)/L5 -> 0.24036236
A7: =LEFT(A6,4)+1&"-"&RIGHT(A6,4)+1 -> 2010-2011 | B7: 21721.69 | C7: =(B7-B6)/B6 -> 0.23243491 | D7: 30990.95 | E7: =(D7-D6)/D6 -> 0.18696523 | F7: 34664.81 | G7: =(F7-F6)/F6 -> 0.11346482 | H7: 276996.7 | I7: =(H7-H6)/H6 -> 0.20268345 | J7: 4125.43 | K7: =(J7-J6)/J6 -> 0.4050905 | L7: 7730.46 | M7: =(L7-L6)/L6 -> -0.017930281
A8: =LEFT(A7,4)+1&"-"&RIGHT(A7,4)+1 -> 2011-2012 | B8: 25718.6 | C8: =(B8-B7)/B7 -> 0.18400548 | D8: 38010.36 | E8: =(D8-D7)/D7 -> 0.2264987 | F8: 46044.62 | G8: =(F8-F7)/F7 -> 0.32828133 | H8: =36404788/100 -> 364047.88 | I8: =(H8-H7)/H7 -> 0.31426793 | J8: 4851.46 | K8: =(J8-J7)/J7 -> 0.17598893 | L8: 12814.77 | M8: =(L8-L7)/L7 -> 0.65769825
A9: =LEFT(A8,4)+1&"-"&RIGHT(A8,4)+1 -> 2012-2013 | B9: 30076.61 | C9: =(B9-B8)/B8 -> 0.16944974 | D9: 44137.31 | E9: =(D9-D8)/D8 -> 0.16119158 | F9: 53488.74 | G9: =(F9-F8)/F8 -> 0.16167187 | H9: =41231300/100 -> 412313 | I9: =(H9-H8)/H8 -> 0.13257904 | J9: 5739.44 | K9: =(J9-J8)/J8 -> 0.18303356 | L9: 15002.47 | M9: =(L9-L8)/L8 -> 0.17071707
A10: =LEFT(A9,4)+1&"-"&RIGHT(A9,4)+1 -> 2013-2014 | B10: 31995.02 | C10: =(B10-B9)/B9 -> 0.063784117 | D10: 49176.94 | E10: =(D10-D9)/D9 -> 0.11418072 | F10: 60485.5 | G10: =(F10-F9)/F9 -> 0.13080809 | H10: =46504121/100 -> 465041.21 | I10: =(H10-H9)/H9 -> 0.12788394 | J10: 5758.5 | K10: =(J10-J9)/J9 -> 0.0033208815 | L10: 16944.12 | M10: =(L10-L9)/L9 -> 0.12942202
A11: =LEFT(A10,4)+1&"-"&RIGHT(A10,4)+1 -> 2014-2015 | B11: 35232.5 | C11: =(B11-B10)/B10 -> 0.101187 | D11: 57950.47 | E11: =(D11-D10)/D10 -> 0.1784074 | F11: 71746.43 | G11: =(F11-F10)/F10 -> 0.1861757 | H11: =51256405/100 -> 512564.05 | I11: =(H11-H10)/H10 -> 0.1021906 | J11: 4997.68 | K11: =(J11-J10)/J10 -> -0.13212121 | L11: 18641.73 | M11: =(L11-L10)/L10 -> 0.10018874
A12: =LEFT(A11,4)+1&"-"&RIGHT(A11,4)+1 -> 2015-2016 | B12: 38995.15 | C12: =(B12-B11)/B11 -> 0.10679486 | D12: 69032.66 | E12: =(D12-D11)/D11 -> 0.19123555 | F12: 78689.47 | G12: =(F12-F11)/F11 -> 0.096771923 | H12: =56199361/100 -> 561993.61 | I12: =(H12-H11)/H11 -> 0.09643587 | J12: 8342.29 | K12: =(J12-J11)/J11 -> 0.66923252 | L12: 17818.39 | M12: =(L12-L11)/L11 -> -0.044166502
A13: =LEFT(A12,4)+1&"-"&RIGHT(A12,4)+1 -> 2016-2017 | B13: 42176.38 | C13: =(B13-B12)/B12 -> 0.081580145 | D13: 75611.72 | E13: =(D13-D12)/D12 -> 0.095303585 | F13: 91096.31 | G13: =(F13-F12)/F12 -> 0.15766836 | H13: =63488640/100 -> 634886.4 | I13: =(H13-H12)/H12 -> 0.12970395 | J13: 11286.25 | K13: =(J13-J12)/J12 -> 0.35289591 | L13: 26448.35 | M13: =(L13-L12)/L12 -> 0.48432883
A14: =LEFT(A13,4)+1&"-"&RIGHT(A13,4)+1 -> 2017-2018 | B14: 46459.61 | C14: =(B14-B13)/B13 -> 0.10155518 | D14: 83020.14 | E14: =(D14-D13)/D13 -> 0.097979784 | F14: 99948.35 | G14: =(F14-F13)/F13 -> 0.097172322 | H14: =70158826/100 -> 701588.26 | I14: =(H14-H13)/H13 -> 0.10506109 | J14: 10289.46 | K14: =(J14-J13)/J13 -> -0.088318972 | L14: 26837.41 | M14: =(L14-L13)/L13 -> 0.01471018
A15: =LEFT(A14,4)+1&"-"&RIGHT(A14,4)+1 -> 2018-2019 | B15: 50644.1 | C15: =(B15-B14)/B14 -> 0.090067265 | D15: 92854.47 | E15: =(D15-D14)/D14 -> 0.11845716 | F15: 110316.39 | G15: =(F15-F14)/F14 -> 0.10373398 | H15: =78828558/100 -> 788285.58 | I15: =(H15-H14)/H14 -> 0.12357293 | J15: 9753.43 | K15: =(J15-J14)/J14 -> -0.052095056 | L15: 26958.3 | M15: =(L15-L14)/L14 -> 0.004504533
A16: =LEFT(A15,4)+1&"-"&RIGHT(A15,4)+1 -> 2019-2020 | B16: 50323.14 | C16: =(B16-B15)/B15 -> -0.0063375596 | D16: 90224.67 | E16: =(D16-D15)/D15 -> -0.028321738 | F16: 104719.92 | G16: =(F16-F15)/F15 -> -0.050731084 | H16: =81293463/100 -> 812934.63 | I16: =(H16-H15)/H15 -> 0.031269188 | J16: 9665.02 | K16: =(J16-J15)/J15 -> -0.0090645035 | L16: 23837.48 | M16: =(L16-L15)/L15 -> -0.11576472
A17: =LEFT(A16,4)+1&"-"&RIGHT(A16,4)+1 -> 2020-2021 | B17: 47660.84 | C17: =(B17-B16)/B16 -> -0.052904091 | D17: 97616.83 | E17: =(D17-D16)/D16 -> 0.081930585 | F17: 123446.33 | G17: =(F17-F16)/F16 -> 0.17882376 | H17: =77172389/100 -> 771723.89 | I17: =(H17-H16)/H16 -> -0.050693793 | J17: 15438.16 | K17: =(J17-J16)/J16 -> 0.59732313 | L17: 35203.69 | M17: =(L17-L16)/L16 -> 0.47682096
A18: =LEFT(A17,4)+1&"-"&RIGHT(A17,4)+1 -> 2021-2022 | B18: 58340.52 | C18: =(B18-B17)/B17 -> 0.22407662 | D18: 116640.24 | E18: =(D18-D17)/D17 -> 0.19487838 | F18: 146179.51 | G18: =(F18-F17)/F17 -> 0.18415436 | H18: =92446542/100 -> 924465.42 | I18: =(H18-H17)/H17 -> 0.19792251 | J18: 17046.02 | K18: =(J18-J17)/J17 -> 0.10414842 | L18: 37306.47 | M18: =(L18-L17)/L17 -> 0.059731807
A19: =LEFT(A18,4)+1&"-"&RIGHT(A18,4)+1 -> 2022-2023 | B19: 71968.16 | C19: =(B19-B18)/B18 -> 0.23358791 | D19: 132724.65 | E19: =(D19-D18)/D18 -> 0.13789761 | F19: 141950.94 | G19: =(F19-F18)/F18 -> -0.028927242 | H19: =103873406/100 -> 1038734.1 | I19: =(H19-H18)/H18 -> 0.1236051 | J19: 16787.49 | K19: =(J19-J18)/J18 -> -0.01516659 | L19: 25554.54 | M19: =(L19-L18)/L18 -> -0.31501051
A20: =LEFT(A19,4)+1&"-"&RIGHT(A19,4)+1 -> 2023-2024 | B20: 74329.01 | C20: =(B20-B19)/B19 -> 0.03280409 | D20: 124486.15 | E20: =(D20-D19)/D19 -> -0.062072117 | F20: 142626.34 | G20: =(F20-F19)/F19 -> 0.0047579819 | H20: =113537156/100 -> 1135371.6 | I20: =(H20-H19)/H19 -> 0.093033919 | J20: 16880.17 | K20: =(J20-J19)/J19 -> 0.0055207777 | L20: 34258.05 | M20: =(L20-L19)/L19 -> 0.34058567
A21: =LEFT(A20,4)+1&"-"&RIGHT(A20,4)+1 -> 2024-2025 | B21: 76642.2 | C21: =(B21-B20)/B20 -> 0.031120958 | D21: 124861.07 | E21: =(D21-D20)/D20 -> 0.0030117407 | F21: 155920.79 | G21: =(F21-F20)/F20 -> 0.093211745 | H21: =124853301/100 -> 1248533 | I21: =(H21-H20)/H20 -> 0.09966909 | J21: 17886.77 | K21: =(J21-J20)/J20 -> 0.059632101 | L21: 48248.14 | M21: =(L21-L20)/L20 -> 0.4083738
A27: VARIABLE | B27: HIGHEST GROWTH% | C27: YEAR | D27: LOWEST GROWTH % | E27: YEAR
A28: OWN TAX REVENUE | B28: 0.2336 | C28: 2022-23 | D28: -0.0529 | E28: 2020-21
A29: REVENUE RECEIPT | B29: 0.2265 | C29: 2011-12 | D29: -0.0621 | E29: 2023-24
A30: REVENUE EXPENDITURE | B30: 0.3283 | C30: 2011-12 | D30: -0.0507 | E30: 2019-20
A31: CAPITAL EXPENDITURE | B31: =MAX(K3:K21) -> 0.89121145 | C31: 2007-08 | D31: =MIN(K3:K21) -> -0.13212121 | E31: 2014-15
A32: FISCAL DEFICIT | B32: =MAX(M3:M21) -> 0.65769825 | C32: 2011-12 | D32: =MIN(M3:M21) -> -0.31501051 | E32: 2022-23
A33: GSDP | B33: 0.3143 | C33: 2011-12 | D33: -0.0507 | E33: 2020-21

Sheet GROWTH CHARTS

Sheet FISCAL STRESS SCORE
A1: YEAR | B1: RR RATIO | C1: RE RATIO | D1: RD RATIO | E1: Z RR | F1: Z RE | G1: Z RD | H1: CE RATIO | I1: TE RATIO | J1: FD RATIO | K1: Z CE | L1: Z TE | M1: Z FD | N1: FISCAL STRESS SCORE | O1: RANK
A2: 2005-2006 | B2: 12.3 | C2: 14.81 | D2: 2.52 | E2: =($B$23-B2)/$B$24 -> -0.79020255 | F2: =(C2-$C$23)/$C$24 -> 0.97007535 | G2: =(D2-$D$23)/$D$24 -> 0.58725758 | H2: 0.89 | I2: 15.7 | J2: 3.36 | K2: =($H$23-H2)/$H$24 -> 1.7032575 | L2: =($I$23-I2)/$I$24 -> -0.43879369 | M2: =($J$23-J2)/$J$24 -> 0.15256283 | N2: =AVERAGE(E2:G2,K2:M2) -> 0.36402617 | O2: =RANK(N2,$N$2:$N$21,1) -> 19
A3: =LEFT(A2,4)+1&"-"&RIGHT(A2,4)+1 -> 2006-2007 | B3: 12.77 | C3: 14.62 | D3: 1.85 | E3: =($B$23-B3)/$B$24 -> -1.3516465 | F3: =(C3-$C$23)/$C$24 -> 0.78446174 | G3: =(D3-$D$23)/$D$24 -> -0.56828597 | H3: 0.88 | I3: 15.5 | J3: 2.68 | K3: =($H$23-H3)/$H$24 -> 1.7377015 | L3: =($I$23-I3)/$I$24 -> -0.26310052 | M3: =($J$23-J3)/$J$24 -> 1.4575028 | N3: =AVERAGE(E3:G3,K3:M3) -> 0.29943884 | O3: =RANK(N3,$N$2:$N$21,1) -> 17
A4: =LEFT(A3,4)+1&"-"&RIGHT(A3,4)+1 -> 2007-2008 | B4: 12.05 | C4: 14.21 | D4: 2.16 | E4: =($B$23-B4)/$B$24 -> -0.49156213 | F4: =(C4-$C$23)/$C$24 -> 0.3839271 | G4: =(D4-$D$23)/$D$24 -> -0.033631491 | H4: 1.35 | I4: 15.56 | J4: 3.48 | K4: =($H$23-H4)/$H$24 -> 0.11883192 | L4: =($I$23-I4)/$I$24 -> -0.31580847 | M4: =($J$23-J4)/$J$24 -> -0.077720689 | N4: =AVERAGE(E4:G4,K4:M4) -> -0.069327294 | O4: =RANK(N4,$N$2:$N$21,1) -> 8
A5: =LEFT(A4,4)+1&"-"&RIGHT(A4,4)+1 -> 2008-2009 | B5: 12.19 | C5: 14.04 | D5: 1.85 | E5: =($B$23-B5)/$B$24 -> -0.65880077 | F5: =(C5-$C$23)/$C$24 -> 0.21785177 | G5: =(D5-$D$23)/$D$24 -> -0.56828597 | H5: 1.33 | I5: 15.37 | J5: 3.16 | K5: =($H$23-H5)/$H$24 -> 0.18771998 | L5: =($I$23-I5)/$I$24 -> -0.14889996 | M5: =($J$23-J5)/$J$24 -> 0.53636871 | N5: =AVERAGE(E5:G5,K5:M5) -> -0.07234104 | O5: =RANK(N5,$N$2:$N$21,1) -> 7
A6: =LEFT(A5,4)+1&"-"&RIGHT(A5,4)+1 -> 2009-2010 | B6: 11.34 | C6: 13.52 | D6: 2.18 | E6: =($B$23-B6)/$B$24 -> 0.35657666 | F6: =(C6-$C$23)/$C$24 -> -0.29014338 | G6: =(D6-$D$23)/$D$24 -> 0.00086234593 | H6: 1.27 | I6: 14.79 | J6: 3.42 | K6: =($H$23-H6)/$H$24 -> 0.39438419 | L6: =($I$23-I6)/$I$24 -> 0.36061023 | M6: =($J$23-J6)/$J$24 -> 0.037421073 | N6: =AVERAGE(E6:G6,K6:M6) -> 0.14328519 | O6: =RANK(N6,$N$2:$N$21,1) -> 13
A7: =LEFT(A6,4)+1&"-"&RIGHT(A6,4)+1 -> 2010-2011 | B7: 11.19 | C7: 12.51 | D7: 1.33 | E7: =($B$23-B7)/$B$24 -> 0.53576091 | F7: =(C7-$C$23)/$C$24 -> -1.2768263 | G7: =(D7-$D$23)/$D$24 -> -1.4651257 | H7: 1.49 | I7: 14 | J7: 2.79 | K7: =($H$23-H7)/$H$24 -> -0.36338456 | L7: =($I$23-I7)/$I$24 -> 1.0545983 | M7: =($J$23-J7)/$J$24 -> 1.2464096 | N7: =AVERAGE(E7:G7,K7:M7) -> -0.044761304 | O7: =RANK(N7,$N$2:$N$21,1) -> 9
A8: =LEFT(A7,4)+1&"-"&RIGHT(A7,4)+1 -> 2011-2012 | B8: 10.44 | C8: 12.65 | D8: 2.21 | E8: =($B$23-B8)/$B$24 -> 1.4316822 | F8: =(C8-$C$23)/$C$24 -> -1.1400583 | G8: =(D8-$D$23)/$D$24 -> 0.052603102 | H8: 1.33 | I8: 13.98 | J8: 3.52 | K8: =($H$23-H8)/$H$24 -> 0.18771998 | L8: =($I$23-I8)/$I$24 -> 1.0721676 | M8: =($J$23-J8)/$J$24 -> -0.15448186 | N8: =AVERAGE(E8:G8,K8:M8) -> 0.24160544 | O8: =RANK(N8,$N$2:$N$21,1) -> 15
A9: =LEFT(A8,4)+1&"-"&RIGHT(A8,4)+1 -> 2012-2013 | B9: 10.7 | C9: 12.97 | D9: 2.27 | E9: =($B$23-B9)/$B$24 -> 1.1210961 | F9: =(C9-$C$23)/$C$24 -> -0.82744595 | G9: =(D9-$D$23)/$D$24 -> 0.15608461 | H9: 1.39 | I9: 14.36 | J9: 3.64 | K9: =($H$23-H9)/$H$24 -> -0.018944219 | L9: =($I$23-I9)/$I$24 -> 0.73835055 | M9: =($J$23-J9)/$J$24 -> -0.38476539 | N9: =AVERAGE(E9:G9,K9:M9) -> 0.13072929 | O9: =RANK(N9,$N$2:$N$21,1) -> 12
A10: =LEFT(A9,4)+1&"-"&RIGHT(A9,4)+1 -> 2013-2014 | B10: 10.57 | C10: 13.01 | D10: 2.43 | E10: =($B$23-B10)/$B$24 -> 1.2763892 | F10: =(C10-$C$23)/$C$24 -> -0.7883694 | G10: =(D10-$D$23)/$D$24 -> 0.43203531 | H10: 1.24 | I10: 14.24 | J10: 3.64 | K10: =($H$23-H10)/$H$24 -> 0.49771629 | L10: =($I$23-I10)/$I$24 -> 0.84376645 | M10: =($J$23-J10)/$J$24 -> -0.38476539 | N10: =AVERAGE(E10:G10,K10:M10) -> 0.3127954 | O10: =RANK(N10,$N$2:$N$21,1) -> 18
A11: =LEFT(A10,4)+1&"-"&RIGHT(A10,4)+1 -> 2014-2015 | B11: 11.31 | C11: 14 | D11: 2.69 | E11: =($B$23-B11)/$B$24 -> 0.39241351 | F11: =(C11-$C$23)/$C$24 -> 0.17877522 | G11: =(D11-$D$23)/$D$24 -> 0.8804552 | H11: 0.98 | I11: 14.97 | J11: 3.64 | K11: =($H$23-H11)/$H$24 -> 1.3932612 | L11: =($I$23-I11)/$I$24 -> 0.20248638 | M11: =($J$23-J11)/$J$24 -> -0.38476539 | N11: =AVERAGE(E11:G11,K11:M11) -> 0.44377101 | O11: =RANK(N11,$N$2:$N$21,1) -> 20
A12: =LEFT(A11,4)+1&"-"&RIGHT(A11,4)+1 -> 2015-2016 | B12: 12.28 | C12: 14 | D12: 1.72 | E12: =($B$23-B12)/$B$24 -> -0.76631132 | F12: =(C12-$C$23)/$C$24 -> 0.17877522 | G12: =(D12-$D$23)/$D$24 -> -0.79249591 | H12: 1.48 | I12: 15.49 | J12: 3.17 | K12: =($H$23-H12)/$H$24 -> -0.32894052 | L12: =($I$23-I12)/$I$24 -> -0.25431586 | M12: =($J$23-J12)/$J$24 -> 0.51717841 | N12: =AVERAGE(E12:G12,K12:M12) -> -0.24101833 | O12: =RANK(N12,$N$2:$N$21,1) -> 5
A13: =LEFT(A12,4)+1&"-"&RIGHT(A12,4)+1 -> 2016-2017 | B13: 11.91 | C13: 14.35 | D13: 2.44 | E13: =($B$23-B13)/$B$24 -> -0.3243235 | F13: =(C13-$C$23)/$C$24 -> 0.52069503 | G13: =(D13-$D$23)/$D$24 -> 0.44928223 | H13: 1.78 | I13: 16.13 | J13: 4.17 | K13: =($H$23-H13)/$H$24 -> -1.3622615 | L13: =($I$23-I13)/$I$24 -> -0.81653401 | M13: =($J$23-J13)/$J$24 -> -1.401851 | N13: =AVERAGE(E13:G13,K13:M13) -> -0.48916546 | O13: =RANK(N13,$N$2:$N$21,1) -> 2
A14: =LEFT(A13,4)+1&"-"&RIGHT(A13,4)+1 -> 2017-2018 | B14: 11.83 | C14: 14.25 | D14: 2.41 | E14: =($B$23-B14)/$B$24 -> -0.22875856 | F14: =(C14-$C$23)/$C$24 -> 0.42300365 | G14: =(D14-$D$23)/$D$24 -> 0.39754147 | H14: 1.47 | I14: 15.71 | J14: 3.83 | K14: =($H$23-H14)/$H$24 -> -0.29449649 | L14: =($I$23-I14)/$I$24 -> -0.44757835 | M14: =($J$23-J14)/$J$24 -> -0.74938097 | N14: =AVERAGE(E14:G14,K14:M14) -> -0.14994487 | O14: =RANK(N14,$N$2:$N$21,1) -> 6
... A21: =LEFT(A20,4)+1&"-"&RIGHT(A20,4)+1 -> 2024-2025 | B21: 10 | C21: 12.49 | D21: 2.49 | E21: =($B$23-B21)/$B$24 -> 1.9572893 | F21: =(C21-$C$23)/$C$24 -> -1.2963645 | G21: =(D21-$D$23)/$D$24 -> 0.53551682 | H21: 1.43 | I21: 13.92 | J21: 3.86 | K21: =($H$23-H21)/$H$24 -> -0.15672035 | L21: =($I$23-I21)/$I$24 -> 1.1248755 | M21: =($J$23-J21)/$J$24 -> -0.80695185 | N21: =AVERAGE(E21:G21,K21:M21) -> 0.22627415 | O21: =RANK(N21,$N$2:$N$21,1) -> 14
A23: AVERAGE | B23: =AVERAGE(B2:B21) -> 11.6385 | C23: =AVERAGE(C2:C21) -> 13.817 | D23: =AVERAGE(D2:D21) -> 2.1795 | H23: =AVERAGE(H2:H21) -> 1.3845 | I23: =AVERAGE(I2:I21) -> 15.2005 | J23: =AVERAGE(J2:J21) -> 3.4395
A24: SD | B24: =_xlfn.STDEV.S(B2:B21) -> 0.83712714 | C24: =_xlfn.STDEV.S(C2:C21) -> 1.0236318 | D24: =_xlfn.STDEV.S(D2:D21) -> 0.57981372 | H24: =_xlfn.STDEV.S(H2:H21) -> 0.29032604 | I24: =_xlfn.STDEV.S(I2:I21) -> 1.1383482 | J24: =_xlfn.STDEV.S(J2:J21) -> 0.52109677

Sheet FISCAL STRESS
A1: YEAR | B1: FISCAL STRESS SCORE | C1: RANK
A2: 2005-2006 | B2: 0.36402617 | C2: 19
A3: =LEFT(A2,4)+1&"-"&RIGHT(A2,4)+1 -> 2006-2007 | B3: 0.29943884 | C3: 17 | G3: TOP 5 HIGHEST FISCAL STRESS YEARS
A4: =LEFT(A3,4)+1&"-"&RIGHT(A3,4)+1 -> 2007-2008 | B4: -0.069327294 | C4: 8 | G4: RANK | H4: YEAR | I4: FISCAL STRESS SCORE
A5: =LEFT(A4,4)+1&"-"&RIGHT(A4,4)+1 -> 2008-2009 | B5: -0.07234104 | C5: 7 | G5: 1 | H5: =INDEX($A$2:$A$21,MATCH(G5,$C$2:$C$21,0)) -> 2020-2021 | I5: =INDEX($B$2:$B$21,MATCH(G5,$C$2:$C$21,0)) -> -0.6310854
A6: =LEFT(A5,4)+1&"-"&RIGHT(A5,4)+1 -> 2009-2010 | B6: 0.14328519 | C6: 13 | G6: 2 | H6: =INDEX($A$2:$A$21,MATCH(G6,$C$2:$C$21,0)) -> 2016-2017 | I6: =INDEX($B$2:$B$21,MATCH(G6,$C$2:$C$21,0)) -> -0.48916546
A7: =LEFT(A6,4)+1&"-"&RIGHT(A6,4)+1 -> 2010-2011 | B7: -0.044761304 | C7: 9 | G7: 3 | H7: =INDEX($A$2:$A$21,MATCH(G7,$C$2:$C$21,0)) -> 2022-2023 | I7: =INDEX($B$2:$B$21,MATCH(G7,$C$2:$C$21,0)) -> -0.45541573
A8: =LEFT(A7,4)+1&"-"&RIGHT(A7,4)+1 -> 2011-2012 | B8: 0.24160544 | C8: 15 | G8: 4 | H8: =INDEX($A$2:$A$21,MATCH(G8,$C$2:$C$21,0)) -> 2021-2022 | I8: =INDEX($B$2:$B$21,MATCH(G8,$C$2:$C$21,0)) -> -0.39121913
A9: =LEFT(A8,4)+1&"-"&RIGHT(A8,4)+1 -> 2012-2013 | B9: 0.13072929 | C9: 12 | G9: 5 | H9: =INDEX($A$2:$A$21,MATCH(G9,$C$2:$C$21,0)) -> 2015-2016 | I9: =INDEX($B$2:$B$21,MATCH(G9,$C$2:$C$21,0)) -> -0.24101833
A10: =LEFT(A9,4)+1&"-"&RIGHT(A9,4)+1 -> 2013-2014 | B10: 0.3127954 | C10: 18
A11: =LEFT(A10,4)+1&"-"&RIGHT(A10,4)+1 -> 2014-2015 | B11: 0.44377101 | C11: 20
A12: =LEFT(A11,4)+1&"-"&RIGHT(A11,4)+1 -> 2015-2016 | B12: -0.24101833 | C12: 5
A13: =LEFT(A12,4)+1&"-"&RIGHT(A12,4)+1 -> 2016-2017 | B13: -0.48916546 | C13: 2 | G13: TOP 5 LOWEST FISCAL STRESS YEARS
A14: =LEFT(A13,4)+1&"-"&RIGHT(A13,4)+1 -> 2017-2018 | B14: -0.14994487 | C14: 6 | G14: RANK | H14: YEAR | I14: FISCAL STRESS SCORE
A15: =LEFT(A14,4)+1&"-"&RIGHT(A14,4)+1 -> 2018-2019 | B15: 0.09650804 | C15: 11 | G15: 20 | H15: =INDEX($A$2:$A$21,MATCH(G15,$C$2:$C$21,0)) -> 2014-2015 | I15: =INDEX($B$2:$B$21,MATCH(G15,$C$2:$C$21,0)) -> 0.44377101
A16: =LEFT(A15,4)+1&"-"&RIGHT(A15,4)+1 -> 2019-2020 | B16: 0.27994607 | C16: 16 | G16: 19 | H16: =INDEX($A$2:$A$21,MATCH(G16,$C$2:$C$21,0)) -> 2005-2006 | I16: =INDEX($B$2:$B$21,MATCH(G16,$C$2:$C$21,0)) -> 0.36402617
A17: =LEFT(A16,4)+1&"-"&RIGHT(A16,4)+1 -> 2020-2021 | B17: -0.6310854 | C17: 1 | G17: 18 | H17: =INDEX($A$2:$A$21,MATCH(G17,$C$2:$C$21,0)) -> 2013-2014 | I17: =INDEX($B$2:$B$21,MATCH(G17,$C$2:$C$21,0)) -> 0.3127954
A18: =LEFT(A17,4)+1&"-"&RIGHT(A17,4)+1 -> 2021-2022 | B18: -0.39121913 | C18: 4 | G18: 17 | H18: =INDEX($A$2:$A$21,MATCH(G18,$C$2:$C$21,0)) -> 2006-2007 | I18: =INDEX($B$2:$B$21,MATCH(G18,$C$2:$C$21,0)) -> 0.29943884
A19: =LEFT(A18,4)+1&"-"&RIGHT(A18,4)+1 -> 2022-2023 | B19: -0.45541573 | C19: 3 | G19: 16 | H19: =INDEX($A$2:$A$21,MATCH(G19,$C$2:$C$21,0)) -> 2019-2020 | I19: =INDEX($B$2:$B$21,MATCH(G19,$C$2:$C$21,0)) -> 0.27994607
A20: =LEFT(A19,4)+1&"-"&RIGHT(A19,4)+1 -> 2023-2024 | B20: 0.005898968 | C20: 10
A21: =LEFT(A20,4)+1&"-"&RIGHT(A20,4)+1 -> 2024-2025 | B21: 0.22627415 | C21: 14
